loggar/__init__.py
loggar/loggar.py
loggar/__pycache__/__init__.cpython-312.pyc
loggar/libs/_version.py
loggar/libs/argparser.py
loggar/libs/changelog.py
loggar/libs/config.py
loggar/libs/config.toml
loggar/libs/database.py
loggar/libs/enums.py
loggar/libs/utilities.py
loggar/libs/__pycache__/_version.cpython-312.pyc
loggar/meta/database/setup/create_db.sql
loggar/meta/database/setup/create_table__access_failure.sql
loggar/meta/database/setup/create_table__access_success.sql
loggar/meta/database/setup/header
loggar/meta/deployment/scripts/nopasswd-lastb
loggar/objects/_baselogobject.py
loggar/objects/accesslogobject.py
loggar/readers/_basereader.py
loggar/readers/lastreader.py
loggar-0.1.2.dist-info/licenses/LICENSE
loggar-0.1.2.dist-info/METADATA
loggar-0.1.2.dist-info/WHEEL
loggar-0.1.2.dist-info/entry_points.txt
loggar-0.1.2.dist-info/top_level.txt
loggar-0.1.2.dist-info/RECORD
