Metadata-Version: 2.4
Name: loggar
Version: 0.1.2
Summary: A utility for archiving Linux log files.
Author-email: The Developers <development@s3dev.uk>
License-Expression: MIT
Project-URL: Documentation, https://loggar.readthedocs.io/en/latest/index.html
Project-URL: Homepage, https://github.com/s3dev/loggar
Project-URL: Repository, https://github.com/s3dev/loggar
Keywords: utility,utilities,archiving
Classifier: Development Status :: 4 - Beta
Classifier: Intended Audience :: Developers
Classifier: Intended Audience :: Information Technology
Classifier: Intended Audience :: System Administrators
Classifier: Operating System :: POSIX :: Linux
Classifier: Operating System :: Microsoft :: Windows
Classifier: Programming Language :: Python :: 3.10
Classifier: Programming Language :: Python :: 3.11
Classifier: Programming Language :: Python :: 3.12
Classifier: Programming Language :: Python :: 3.13
Classifier: Programming Language :: Python :: Implementation :: CPython
Classifier: Topic :: System :: Archiving
Classifier: Topic :: System :: Archiving :: Backup
Classifier: Topic :: System :: Logging
Classifier: Topic :: System :: Systems Administration
Classifier: Topic :: Utilities
Requires-Python: >=3.9
License-File: LICENSE
Requires-Dist: dbilib
Requires-Dist: pandas
Dynamic: license-file
